pypcom/__init__.py
pypcom/__version__.py
pypcom/component.py
pypcom/expected_conditions.py
pypcom/page.py
pypcom/pytest_plugin.py
pypcom/common/__init__.py
pypcom/common/iframe.py
pypcom/state/__init__.py
pypcom/state/expected_attribute.py
pypcom/state/state.py
PyPCOM-1.2.1.dist-info/LICENSE
PyPCOM-1.2.1.dist-info/METADATA
PyPCOM-1.2.1.dist-info/WHEEL
PyPCOM-1.2.1.dist-info/entry_points.txt
PyPCOM-1.2.1.dist-info/top_level.txt
PyPCOM-1.2.1.dist-info/RECORD
