Metadata-Version: 2.1
Name: PyPCOM
Version: 1.2.1
Summary: Python Page Component Object Model for Selenium
Home-page: https://github.com/SalmonMode/PyPCOM
Author: Chris NeJame
Author-email: Chris.T.NeJame@gmail.com
License: MIT
Download-URL: https://github.com/SalmonMode/PyPCOM/archive/1.2.1.tar.gz
Keywords: testing test-automation functional-testing testing-tools test tests development organization
Platform: UNKNOWN
Classifier: Intended Audience :: Developers
Classifier: Topic :: Software Development :: Testing
Classifier: Topic :: Software Development :: Quality Assurance
Classifier: License :: OSI Approved :: MIT License
Classifier: Programming Language :: Python :: 2.7
Classifier: Programming Language :: Python :: 3
Classifier: Programming Language :: Python :: 3.0
Classifier: Programming Language :: Python :: 3.1
Classifier: Programming Language :: Python :: 3.2
Classifier: Programming Language :: Python :: 3.3
Classifier: Programming Language :: Python :: 3.4
Classifier: Programming Language :: Python :: 3.5
Classifier: Programming Language :: Python :: 3.6
Requires-Dist: selenium
